winclip32/__init__.py
winclip32/errors.py
winclip32/main.py
winclip32-0.6.0.dist-info/LICENCE.txt
winclip32-0.6.0.dist-info/METADATA
winclip32-0.6.0.dist-info/WHEEL
winclip32-0.6.0.dist-info/top_level.txt
winclip32-0.6.0.dist-info/RECORD
