Metadata-Version: 2.1
Name: winclip32
Version: 0.6.0
Summary: This is a small library for windows OS to work with clipboard data storage
Home-page: https://github.com/PyPcDeV/winclip32
Author: PyPcDeV
Author-email: pypcdev@gmail.com
License: UNKNOWN
Platform: UNKNOWN
Classifier: Programming Language :: Python :: 3
Classifier: License :: OSI Approved :: MIT License
Classifier: Operating System :: OS Independent
Requires-Python: >=3.6
Requires-Dist: pywin32
